litai/__about__.py
litai/__init__.py
litai/llm.py
litai/llm_config.py
litai/tools.py
litai/utils/__init__.py
litai/utils/supported_public_models.py
litai/utils/update_model_list.py
litai/utils/utils.py
litai-0.0.10.dist-info/licenses/LICENSE
litai-0.0.10.dist-info/METADATA
litai-0.0.10.dist-info/WHEEL
litai-0.0.10.dist-info/top_level.txt
litai-0.0.10.dist-info/RECORD
