Metadata-Version: 2.4
Name: litai
Version: 0.0.10
Summary: Easiest way to access any AI model with a single subscription.
Home-page: https://github.com/Lightning-AI/LitAI
Download-URL: https://github.com/Lightning-AI/litAI
Author: Lightning-AI et al.
Author-email: community@lightning.ai
Project-URL: Bug Tracker, https://github.com/Lightning-AI/LightningLLM/issues
Project-URL: Documentation, https://lightning-ai.github.io/LightningLLM/
Project-URL: Source Code, https://github.com/Lightning-AI/LightningLLM
Keywords: deep learning,pytorch,AI
Classifier: Environment :: Console
Classifier: Natural Language :: English
Classifier: Development Status :: 3 - Alpha
Classifier: Intended Audience :: Developers
Classifier: Topic :: Scientific/Engineering :: Artificial Intelligence
Classifier: Topic :: Scientific/Engineering :: Information Analysis
Classifier: Operating System :: OS Independent
Classifier: Programming Language :: Python :: 3
Classifier: Programming Language :: Python :: 3.8
Classifier: Programming Language :: Python :: 3.9
Classifier: Programming Language :: Python :: 3.10
Classifier: Programming Language :: Python :: 3.11
Requires-Python: >=3.8
License-File: LICENSE
Requires-Dist: lightning_sdk>=2025.08.26
Dynamic: author
Dynamic: author-email
Dynamic: classifier
Dynamic: description
Dynamic: description-content-type
Dynamic: download-url
Dynamic: home-page
Dynamic: keywords
Dynamic: license-file
Dynamic: project-url
Dynamic: requires-dist
Dynamic: requires-python
Dynamic: summary
